sh_molli/__init__.py
sh_molli/__main__.py
sh_molli/command_line.py
sh_molli/sh_molli.py
sh_molli/sh_molli_fit.py
sh_molli-0.0.55.dist-info/LICENSE
sh_molli-0.0.55.dist-info/METADATA
sh_molli-0.0.55.dist-info/WHEEL
sh_molli-0.0.55.dist-info/entry_points.txt
sh_molli-0.0.55.dist-info/top_level.txt
sh_molli-0.0.55.dist-info/RECORD
